[
  {
    "full_name": "christoomey/vim-tmux-navigator",
    "stargazers_count": 4427,
    "open_issues_count": 53,
    "forks_count": 293
  },
  {
    "full_name": "joshmedeski/t-smart-tmux-session-manager",
    "stargazers_count": 166,
    "open_issues_count": 4,
    "forks_count": 31
  },
  {
    "full_name": "1amSimp1e/dots",
    "stargazers_count": 850,
    "open_issues_count": 7,
    "forks_count": 57
  },
  {
    "full_name": "withastro/astro",
    "stargazers_count": 35541,
    "open_issues_count": 130,
    "forks_count": 1834
  }
]